cytolk/SAAPI32.dll
cytolk/__init__.py
cytolk/__main__.py
cytolk/dolapi32.dll
cytolk/nvdaControllerClient32.dll
cytolk/tolk.cp38-win32.pyd
cytolk/util.py
cytolk-0.1.13.dist-info/LICENSE
cytolk-0.1.13.dist-info/METADATA
cytolk-0.1.13.dist-info/WHEEL
cytolk-0.1.13.dist-info/entry_points.txt
cytolk-0.1.13.dist-info/top_level.txt
cytolk-0.1.13.dist-info/RECORD
