Metadata-Version: 2.1
Name: cytolk
Version: 0.1.13
Summary: A cython wrapper over the tolk library
Home-page: UNKNOWN
License: UNKNOWN
Platform: UNKNOWN
